{
    "os": "Linux-4.15.0-50-generic-x86_64-with-glibc2.27",
    "python": "3.9.18",
    "heartbeatAt": "2023-11-19T11:56:52.146088",
    "startedAt": "2023-11-19T11:56:51.978932",
    "docker": null,
    "cuda": null,
    "args": [],
    "state": "running",
    "program": "/home/m_bobrin/FlashRL/OnlineRL/reinforce.py",
    "codePathLocal": "OnlineRL/reinforce.py",
    "codePath": "OnlineRL/reinforce.py",
    "git": {
        "remote": "https://github.com/skylooop/FlashRL.git",
        "commit": "e448d4f1532f75071bff8a17a1a5ccd98358f427"
    },
    "email": "maksim.bobrin@skoltech.ru",
    "root": "/home/m_bobrin/FlashRL",
    "host": "skoltech-DGX-Station",
    "username": "m_bobrin",
    "executable": "/home/m_bobrin/anaconda3/envs/flashrl/bin/python",
    "cpu_count": 20,
    "cpu_count_logical": 40,
    "cpu_freq": {
        "current": 1358.9723750000003,
        "min": 1200.0,
        "max": 3600.0
    },
    "cpu_freq_per_core": [
        {
            "current": 1492.421,
            "min": 1200.0,
            "max": 3600.0
        },
        {
            "current": 1399.258,
            "min": 1200.0,
            "max": 3600.0
        },
        {
            "current": 1199.35,
            "min": 1200.0,
            "max": 3600.0
        },
        {
            "current": 1299.152,
            "min": 1200.0,
            "max": 3600.0
        },
        {
            "current": 1199.457,
            "min": 1200.0,
            "max": 3600.0
        },
        {
            "current": 1449.111,
            "min": 1200.0,
            "max": 3600.0
        },
        {
            "current": 1199.843,
            "min": 1200.0,
            "max": 3600.0
        },
        {
            "current": 1198.989,
            "min": 1200.0,
            "max": 3600.0
        },
        {
            "current": 1199.154,
            "min": 1200.0,
            "max": 3600.0
        },
        {
            "current": 1399.018,
            "min": 1200.0,
            "max": 3600.0
        },
        {
            "current": 1300.246,
            "min": 1200.0,
            "max": 3600.0
        },
        {
            "current": 1897.968,
            "min": 1200.0,
            "max": 3600.0
        },
        {
            "current": 1901.463,
            "min": 1200.0,
            "max": 3600.0
        },
        {
            "current": 1198.974,
            "min": 1200.0,
            "max": 3600.0
        },
        {
            "current": 1498.352,
            "min": 1200.0,
            "max": 3600.0
        },
        {
            "current": 1199.581,
            "min": 1200.0,
            "max": 3600.0
        },
        {
            "current": 1198.579,
            "min": 1200.0,
            "max": 3600.0
        },
        {
            "current": 1297.121,
            "min": 1200.0,
            "max": 3600.0
        },
        {
            "current": 1299.049,
            "min": 1200.0,
            "max": 3600.0
        },
        {
            "current": 1197.444,
            "min": 1200.0,
            "max": 3600.0
        },
        {
            "current": 1452.428,
            "min": 1200.0,
            "max": 3600.0
        },
        {
            "current": 1390.121,
            "min": 1200.0,
            "max": 3600.0
        },
        {
            "current": 1198.472,
            "min": 1200.0,
            "max": 3600.0
        },
        {
            "current": 1297.716,
            "min": 1200.0,
            "max": 3600.0
        },
        {
            "current": 1200.126,
            "min": 1200.0,
            "max": 3600.0
        },
        {
            "current": 1430.279,
            "min": 1200.0,
            "max": 3600.0
        },
        {
            "current": 1199.643,
            "min": 1200.0,
            "max": 3600.0
        },
        {
            "current": 1198.053,
            "min": 1200.0,
            "max": 3600.0
        },
        {
            "current": 1199.478,
            "min": 1200.0,
            "max": 3600.0
        },
        {
            "current": 1399.508,
            "min": 1200.0,
            "max": 3600.0
        },
        {
            "current": 1297.174,
            "min": 1200.0,
            "max": 3600.0
        },
        {
            "current": 1897.76,
            "min": 1200.0,
            "max": 3600.0
        },
        {
            "current": 1891.186,
            "min": 1200.0,
            "max": 3600.0
        },
        {
            "current": 1198.969,
            "min": 1200.0,
            "max": 3600.0
        },
        {
            "current": 1505.016,
            "min": 1200.0,
            "max": 3600.0
        },
        {
            "current": 1197.871,
            "min": 1200.0,
            "max": 3600.0
        },
        {
            "current": 1199.547,
            "min": 1200.0,
            "max": 3600.0
        },
        {
            "current": 1296.97,
            "min": 1200.0,
            "max": 3600.0
        },
        {
            "current": 1296.134,
            "min": 1200.0,
            "max": 3600.0
        },
        {
            "current": 1200.312,
            "min": 1200.0,
            "max": 3600.0
        }
    ],
    "disk": {
        "/": {
            "total": 1759.8377494812012,
            "used": 1305.7966003417969
        }
    },
    "gpu": "Tesla V100-DGXS-16GB",
    "gpu_count": 4,
    "gpu_devices": [
        {
            "name": "Tesla V100-DGXS-16GB",
            "memory_total": 17179869184
        },
        {
            "name": "Tesla V100-DGXS-16GB",
            "memory_total": 17179869184
        },
        {
            "name": "Tesla V100-DGXS-16GB",
            "memory_total": 17179869184
        },
        {
            "name": "Tesla V100-DGXS-16GB",
            "memory_total": 17179869184
        }
    ],
    "memory": {
        "total": 251.821044921875
    }
}
